fx_bharat/__init__.py
fx_bharat/py.typed
fx_bharat/db/__init__.py
fx_bharat/db/base_backend.py
fx_bharat/db/mongo_backend.py
fx_bharat/db/mysql_backend.py
fx_bharat/db/postgres_backend.py
fx_bharat/db/relational_backend.py
fx_bharat/db/sqlite_backend.py
fx_bharat/db/sqlite_manager.py
fx_bharat/ingestion/__init__.py
fx_bharat/ingestion/lme.py
fx_bharat/ingestion/models.py
fx_bharat/ingestion/rbi_csv.py
fx_bharat/ingestion/rbi_selenium.py
fx_bharat/ingestion/rbi_workbook.py
fx_bharat/ingestion/sbi_pdf.py
fx_bharat/ingestion/strategy.py
fx_bharat/scripts/__init__.py
fx_bharat/scripts/populate_rbi_forex.py
fx_bharat/scripts/populate_sbi_forex.py
fx_bharat/seeds/__init__.py
fx_bharat/seeds/populate_lme.py
fx_bharat/seeds/populate_rbi_forex.py
fx_bharat/seeds/populate_sbi_forex.py
fx_bharat/utils/__init__.py
fx_bharat/utils/date_range.py
fx_bharat/utils/logger.py
fx_bharat/utils/rbi.py
fx_bharat-0.4.1.dist-info/licenses/LICENSE
fx_bharat-0.4.1.dist-info/METADATA
fx_bharat-0.4.1.dist-info/WHEEL
fx_bharat-0.4.1.dist-info/top_level.txt
fx_bharat-0.4.1.dist-info/RECORD
