Metadata-Version: 2.4
Name: fx-bharat
Version: 0.4.1
Summary: Ingestion utilities for downloading and storing RBI forex reference rates
Author-email: Anuj <anuj.k@vindago.in>
Maintainer-email: Vindago Innovations LLC <support@vindago.in>
License: MIT License
Project-URL: Homepage, https://github.com/vindagollc/fx-bharat
Project-URL: Company, https://www.vindago.in/
Classifier: Development Status :: 4 - Beta
Classifier: Programming Language :: Python :: 3
Classifier: Programming Language :: Python :: 3 :: Only
Classifier: License :: OSI Approved :: MIT License
Classifier: Operating System :: OS Independent
Requires-Python: >=3.10
License-File: LICENSE
Requires-Dist: selenium>=4.14
Requires-Dist: webdriver-manager>=4.0
Requires-Dist: html5lib>=1.1
Requires-Dist: pandas>=2.1
Requires-Dist: beautifulsoup4>=4.12
Requires-Dist: SQLAlchemy>=2.0
Requires-Dist: pypdf>=4.2
Requires-Dist: tenacity>=8.2
Requires-Dist: requests>=2.31
Dynamic: license-file
